odoo/addons/base_iso3166/README.rst
odoo/addons/base_iso3166/__init__.py
odoo/addons/base_iso3166/__manifest__.py
odoo/addons/base_iso3166/i18n/base_iso3166.pot
odoo/addons/base_iso3166/i18n/nl.po
odoo/addons/base_iso3166/models/__init__.py
odoo/addons/base_iso3166/models/res_country.py
odoo/addons/base_iso3166/readme/CONTRIBUTORS.rst
odoo/addons/base_iso3166/readme/DESCRIPTION.rst
odoo/addons/base_iso3166/readme/INSTALL.rst
odoo/addons/base_iso3166/readme/ROADMAP.rst
odoo/addons/base_iso3166/readme/USAGE.rst
odoo/addons/base_iso3166/static/description/icon.png
odoo/addons/base_iso3166/static/description/icon.svg
odoo/addons/base_iso3166/static/description/index.html
odoo/addons/base_iso3166/tests/__init__.py
odoo/addons/base_iso3166/tests/test_iso3166.py
odoo/addons/base_iso3166/views/country_view.xml
odoo13_addon_base_iso3166-13.0.1.0.1.dist-info/METADATA
odoo13_addon_base_iso3166-13.0.1.0.1.dist-info/WHEEL
odoo13_addon_base_iso3166-13.0.1.0.1.dist-info/top_level.txt
odoo13_addon_base_iso3166-13.0.1.0.1.dist-info/RECORD
