Metadata-Version: 2.1
Name: odoo13-addon-base-iso3166
Version: 13.0.1.0.1
Summary: ISO 3166
Home-page: https://github.com/OCA/community-data-files
Author: Tecnativa, Creu Blanca, Odoo Community Association (OCA)
Author-email: support@odoo-community.org
License: AGPL-3
Platform: UNKNOWN
Classifier: Programming Language :: Python
Classifier: Framework :: Odoo
Classifier: Framework :: Odoo :: 13.0
Classifier: License :: OSI Approved :: GNU Affero General Public License v3
Classifier: Development Status :: 5 - Production/Stable
Requires-Python: >=3.5
Requires-Dist: odoo (<13.1dev,>=13.0a)
Requires-Dist: pycountry
